{"name":"build-javascript","namedChunkGroups":{"polyfill":{"name":"polyfill","assets":[{"name":"webpack-runtime-c031d41ba7f1c05986b1.js","size":3776},{"name":"polyfill-2234bc869379708d158e.js","size":85836}],"filteredAssets":0,"assetsSize":89612,"filteredAuxiliaryAssets":2,"auxiliaryAssetsSize":223371},"app":{"name":"app","assets":[{"name":"webpack-runtime-c031d41ba7f1c05986b1.js","size":3776},{"name":"framework-d5cb7cfdc68aeef0c65e.js","size":130455},{"name":"styles.00a70db6c4a4e3ad26ee.css","size":16},{"name":"app-69b2c556bb0a88bf6692.js","size":167587}],"filteredAssets":0,"assetsSize":301834,"filteredAuxiliaryAssets":3,"auxiliaryAssetsSize":1047558},"component---src-pages-404-js":{"name":"component---src-pages-404-js","assets":[{"name":"component---src-pages-404-js-04580ef8d0e0c16b9802.js","size":372}],"filteredAssets":0,"assetsSize":372,"filteredAuxiliaryAssets":1,"auxiliaryAssetsSize":513},"component---src-pages-index-js":{"name":"component---src-pages-index-js","assets":[{"name":"component---src-pages-index-js-e0e129edf87dd1eeafbb.js","size":95123}],"filteredAssets":0,"assetsSize":95123,"filteredAuxiliaryAssets":1,"auxiliaryAssetsSize":433058}},"assetsByChunkName":{"polyfill":["webpack-runtime-c031d41ba7f1c05986b1.js","polyfill-2234bc869379708d158e.js"],"app":["webpack-runtime-c031d41ba7f1c05986b1.js","framework-d5cb7cfdc68aeef0c65e.js","styles.00a70db6c4a4e3ad26ee.css","app-69b2c556bb0a88bf6692.js"],"component---src-pages-404-js":["component---src-pages-404-js-04580ef8d0e0c16b9802.js"],"component---src-pages-index-js":["component---src-pages-index-js-e0e129edf87dd1eeafbb.js"]},"childAssetsByChunkName":{}}